fastapi_shield/__init__.py
fastapi_shield/consts.py
fastapi_shield/openapi.py
fastapi_shield/py.typed
fastapi_shield/shield.py
fastapi_shield/typing.py
fastapi_shield/utils.py
fastapi_shield-0.1.5.dist-info/METADATA
fastapi_shield-0.1.5.dist-info/WHEEL
fastapi_shield-0.1.5.dist-info/licenses/LICENSE
fastapi_shield-0.1.5.dist-info/RECORD
