Metadata-Version: 2.4
Name: fastapi-shield
Version: 0.1.5
Summary: A comprehensive FastAPI decorator library providing request validation, authentication, rate limiting, and security shields for API endpoints
Project-URL: Homepage, https://github.com/jimchng/fastapi-shield
Project-URL: Repository, https://github.com/jimchng/fastapi-shield.git
Project-URL: Documentation, https://fastapi-shield.asyncmove.com/
Project-URL: Bug Tracker, https://github.com/jimchng/fastapi-shield/issues
Project-URL: Feature Requests, https://github.com/jimchng/fastapi-shield/discussions
Author-email: Jim Chng <jimchng@outlook.com>
Maintainer-email: Jim Chng <jimchng@outlook.com>
License: MIT
License-File: LICENSE
Keywords: api,async,authentication,decorator,fastapi,python3,rate-limiting,security,shield,validation,web
Classifier: Environment :: Web Environment
Classifier: Framework :: AsyncIO
Classifier: Framework :: FastAPI
Classifier: Intended Audience :: Developers
Classifier: Intended Audience :: System Administrators
Classifier: License :: OSI Approved :: MIT License
Classifier: Operating System :: OS Independent
Classifier: Programming Language :: Python
Classifier: Programming Language :: Python :: 3
Classifier: Programming Language :: Python :: 3 :: Only
Classifier: Programming Language :: Python :: 3.9
Classifier: Programming Language :: Python :: 3.10
Classifier: Programming Language :: Python :: 3.11
Classifier: Programming Language :: Python :: 3.12
Classifier: Programming Language :: Python :: 3.13
Classifier: Topic :: Internet :: WWW/HTTP
Classifier: Topic :: Internet :: WWW/HTTP :: HTTP Servers
Classifier: Topic :: Security
Classifier: Topic :: Software Development :: Libraries :: Application Frameworks
Classifier: Topic :: Software Development :: Libraries :: Python Modules
Classifier: Topic :: System :: Networking
Classifier: Typing :: Typed
Requires-Python: >=3.9
Requires-Dist: fastapi>=0.100.1
Requires-Dist: typing-extensions>=4.0.0; python_version < '3.10'
